umjunsik/__init__.py
umjunsik/__main__.py
umjunsik/umjunsik.py
umjunsik-2.0.2.dist-info/METADATA
umjunsik-2.0.2.dist-info/WHEEL
umjunsik-2.0.2.dist-info/entry_points.txt
umjunsik-2.0.2.dist-info/top_level.txt
umjunsik-2.0.2.dist-info/RECORD
